dvsgc.py
dvsgc-0.1.2.dist-info/METADATA
dvsgc-0.1.2.dist-info/WHEEL
dvsgc-0.1.2.dist-info/licenses/LICENSE
dvsgc-0.1.2.dist-info/RECORD
