Metadata-Version: 2.1
Name: dvsgc
Version: 0.1.2
Summary: DVS-Gestures-Chain. Implementation of the dataset defined in "Spiking Neural Networks for event-based action recognition: A new task to understand their advantage"
Project-URL: Homepage, https://github.com/VicenteAlex/DVS-Gesture-Chain
Project-URL: Bug Tracker, https://github.com/VicenteAlex/DVS-Gesture-Chain/issues
Author-email: VicenteAlex <alex.vicente-sola@strath.ac.uk>
License-File: LICENSE
Classifier: License :: OSI Approved :: MIT License
Classifier: Operating System :: OS Independent
Classifier: Programming Language :: Python :: 3
Requires-Python: >=3.6
Requires-Dist: numpy
Requires-Dist: spikingjelly==0.0.0.0.8
Requires-Dist: torchvision
Requires-Dist: tqdm
